{
  "PackageData": [
    {
      "Row": [
        {
          "SchemaColumnUId": "ae0e45ca-c495-4fe7-a39d-3ab7278e1617",
          "ColumnName": "Id",
          "Value": "1ac63adc-7bfe-4acc-8f67-4098346ce80c"
        },
        {
          "SchemaColumnUId": "736c30a7-c0ec-4fa9-b034-2552b319b633",
          "ColumnName": "Name",
          "Value": "5. Office"
        },
        {
          "SchemaColumnUId": "9e53fd7c-dde4-4502-a64c-b9e34148108b",
          "ColumnName": "Description",
          "Value": ""
        }
      ]
    },
    {
      "Row": [
        {
          "SchemaColumnUId": "ae0e45ca-c495-4fe7-a39d-3ab7278e1617",
          "ColumnName": "Id",
          "Value": "2488ccb5-616c-45de-8cfd-1885669cec15"
        },
        {
          "SchemaColumnUId": "736c30a7-c0ec-4fa9-b034-2552b319b633",
          "ColumnName": "Name",
          "Value": "1. House "
        },
        {
          "SchemaColumnUId": "9e53fd7c-dde4-4502-a64c-b9e34148108b",
          "ColumnName": "Description",
          "Value": ""
        }
      ]
    },
    {
      "Row": [
        {
          "SchemaColumnUId": "ae0e45ca-c495-4fe7-a39d-3ab7278e1617",
          "ColumnName": "Id",
          "Value": "2ff754f3-f6fc-458c-9903-94b2c2dd7aeb"
        },
        {
          "SchemaColumnUId": "736c30a7-c0ec-4fa9-b034-2552b319b633",
          "ColumnName": "Name",
          "Value": "2.Apartment"
        },
        {
          "SchemaColumnUId": "9e53fd7c-dde4-4502-a64c-b9e34148108b",
          "ColumnName": "Description",
          "Value": ""
        }
      ]
    },
    {
      "Row": [
        {
          "SchemaColumnUId": "ae0e45ca-c495-4fe7-a39d-3ab7278e1617",
          "ColumnName": "Id",
          "Value": "78f29101-075c-4dc8-a309-452bbd70fbb2"
        },
        {
          "SchemaColumnUId": "736c30a7-c0ec-4fa9-b034-2552b319b633",
          "ColumnName": "Name",
          "Value": "4. Land area"
        },
        {
          "SchemaColumnUId": "9e53fd7c-dde4-4502-a64c-b9e34148108b",
          "ColumnName": "Description",
          "Value": ""
        }
      ]
    },
    {
      "Row": [
        {
          "SchemaColumnUId": "ae0e45ca-c495-4fe7-a39d-3ab7278e1617",
          "ColumnName": "Id",
          "Value": "e0d31f04-04b6-47c0-a18e-2ba149048f21"
        },
        {
          "SchemaColumnUId": "736c30a7-c0ec-4fa9-b034-2552b319b633",
          "ColumnName": "Name",
          "Value": "3. Parking lot"
        },
        {
          "SchemaColumnUId": "9e53fd7c-dde4-4502-a64c-b9e34148108b",
          "ColumnName": "Description",
          "Value": ""
        }
      ]
    }
  ]
}